basic_gear/__init__.py
basic_gear/cli/__init__.py
basic_gear/cli/shell.py
basic_gear/core/__init__.py
basic_gear/core/cffi_interface.py
basic_gear/core/tor_checks.py
basic_gear/shared_library/libmath_operations.dll
basic_gear/shared_library/libmath_operations.dylib
basic_gear/shared_library/libmath_operations.so
basic_gear/shared_library/libmath_operations_arm.dylib
basic_gear/shared_library/libtor_operations.dll
basic_gear/shared_library/libtor_operations.dylib
basic_gear/shared_library/libtor_operations.so
basic_gear/shared_library/libtor_operations_arm.dylib
basic_gear/src/__init__.py
basic_gear-0.0.0.16.dist-info/LICENSE
basic_gear-0.0.0.16.dist-info/METADATA
basic_gear-0.0.0.16.dist-info/WHEEL
basic_gear-0.0.0.16.dist-info/entry_points.txt
basic_gear-0.0.0.16.dist-info/top_level.txt
basic_gear-0.0.0.16.dist-info/RECORD
